pysmdev.cp312-win_amd64.pyd
libsmdev_python-20240505.dist-info/METADATA
libsmdev_python-20240505.dist-info/WHEEL
libsmdev_python-20240505.dist-info/top_level.txt
libsmdev_python-20240505.dist-info/RECORD
