Metadata-Version: 2.1
Name: libsmdev-python
Version: 20240505
Summary: Python bindings module for libsmdev
Author: Joachim Metz
Author-email: joachim.metz@gmail.com
License: GNU Lesser General Public License v3 or later (LGPLv3+)
Classifier: Development Status :: 3 - Alpha
Classifier: Programming Language :: Python
Requires-Python: >=3.7
